LICENSE
MANIFEST.in
README.md
setup.py
iscsinar/__init__.py
iscsinar/demo.py
iscsinar/iscsinar.py
iscsinar.egg-info/PKG-INFO
iscsinar.egg-info/SOURCES.txt
iscsinar.egg-info/dependency_links.txt
iscsinar.egg-info/entry_points.txt
iscsinar.egg-info/top_level.txt
iscsinar.egg-info/zip-safe