Metadata-Version: 1.1
Name: iscsinar
Version: 0.0.2
Summary: # narcissujsk
